autobloody/__init__.py
autobloody/automation.py
autobloody/database.py
autobloody/main.py
autobloody/proxy_bypass.py
autobloody-1.1.0.dist-info/METADATA
autobloody-1.1.0.dist-info/WHEEL
autobloody-1.1.0.dist-info/entry_points.txt
autobloody-1.1.0.dist-info/licenses/LICENSE
autobloody-1.1.0.dist-info/RECORD
