Metadata-Version: 2.4
Name: autobloody
Version: 1.1.0
Summary: AD Privesc Automation
Project-URL: Homepage, https://github.com/CravateRouge/autobloody
Project-URL: Bug Tracker, https://github.com/CravateRouge/autobloody/issues
Author-email: CravateRouge <baptiste.crepin@ntymail.com>
License-File: LICENSE
Classifier: License :: OSI Approved :: MIT License
Classifier: Operating System :: OS Independent
Classifier: Programming Language :: Python :: 3
Requires-Python: >=3.8
Requires-Dist: bloodyad>=2.3.1
Requires-Dist: neo4j>=5.0.0
